milena/__init__.py
milena/abc.py
milena/sdp/__init__.py
milena/sip/__init__.py
milena/sip/api/__init__.py
milena/sip/api/aor.py
milena/sip/api/authenticationInfo.py
milena/sip/api/cesq.py
milena/sip/api/uri.py
milena/sip/tools/__init__.py
milena/sip/tools/etc.py
milena/sip/tools/eval.py
milena/sip/tools/reading.py
milena/sip/tools/regex.py
milena/sip/tools/writing.py
tests/e2e/__init__.py
tests/e2e/test_aor.py
tests/e2e/test_cseq.py
tests/e2e/test_uri.py
tests/unit/__init__.py
tests/unit/test_sip_tools_eval.py
tests/unit/test_sip_tools_reading.py
tests/unit/test_sip_tools_writing.py
tests/unit/test_sip_toos_etc.py
milena-0.1.1.dist-info/LICENSE.md
milena-0.1.1.dist-info/METADATA
milena-0.1.1.dist-info/WHEEL
milena-0.1.1.dist-info/top_level.txt
milena-0.1.1.dist-info/RECORD
