Metadata-Version: 2.1
Name: milena
Version: 0.1.1
Summary: Milena is a VoIP stack
Home-page: https://github.com/Otoru/Milena
Author: Vitor Hugo de Oliveira Vargas
Author-email: contato@vitoru.dev
License: MIT
Project-URL: Bug Reports, https://github.com/Otoru/Milena/issues
Project-URL: Source Code, https://github.com/Otoru/Milena
Keywords: ESL,FreeSwitch
Platform: UNKNOWN
Classifier: Development Status :: 1 - Planning
Classifier: License :: OSI Approved :: MIT License
Classifier: Intended Audience :: Developers
Classifier: Intended Audience :: Information Technology
Classifier: Intended Audience :: Telecommunications Industry
Classifier: Programming Language :: Python :: 3.7
Classifier: Programming Language :: Python :: 3.8
Classifier: Programming Language :: Python :: 3.9
Classifier: Topic :: Communications :: Telephony
Classifier: Topic :: Software Development
License-File: LICENSE.md
Provides-Extra: dev
Requires-Dist: tox ; extra == 'dev'
Requires-Dist: black ; extra == 'dev'
Requires-Dist: pytest ; extra == 'dev'
